betterproto2_compiler/__init__.py
betterproto2_compiler/casing.py
betterproto2_compiler/py.typed
betterproto2_compiler/settings.py
betterproto2_compiler/compile/__init__.py
betterproto2_compiler/compile/importing.py
betterproto2_compiler/compile/naming.py
betterproto2_compiler/known_types/__init__.py
betterproto2_compiler/known_types/any.py
betterproto2_compiler/known_types/duration.py
betterproto2_compiler/known_types/google_values.py
betterproto2_compiler/known_types/struct.py
betterproto2_compiler/known_types/timestamp.py
betterproto2_compiler/lib/__init__.py
betterproto2_compiler/lib/message_pool.py
betterproto2_compiler/lib/py.typed
betterproto2_compiler/lib/google/__init__.py
betterproto2_compiler/lib/google/protobuf/__init__.py
betterproto2_compiler/lib/google/protobuf/compiler/__init__.py
betterproto2_compiler/plugin/__init__.py
betterproto2_compiler/plugin/__main__.py
betterproto2_compiler/plugin/compiler.py
betterproto2_compiler/plugin/main.py
betterproto2_compiler/plugin/models.py
betterproto2_compiler/plugin/module_validation.py
betterproto2_compiler/plugin/parser.py
betterproto2_compiler/plugin/plugin.bat
betterproto2_compiler/templates/header.py.j2
betterproto2_compiler/templates/service_stub.py.j2
betterproto2_compiler/templates/service_stub_async.py.j2
betterproto2_compiler/templates/service_stub_sync.py.j2
betterproto2_compiler/templates/template.py.j2
betterproto2_compiler-0.9.0.dist-info/METADATA
betterproto2_compiler-0.9.0.dist-info/WHEEL
betterproto2_compiler-0.9.0.dist-info/entry_points.txt
betterproto2_compiler-0.9.0.dist-info/RECORD
